pytubesearch/__init__.py
pytubesearch/client.py
pytubesearch/models.py
pytubesearch-1.0.0.dist-info/licenses/LICENSE
pytubesearch-1.0.0.dist-info/METADATA
pytubesearch-1.0.0.dist-info/WHEEL
pytubesearch-1.0.0.dist-info/top_level.txt
pytubesearch-1.0.0.dist-info/RECORD
