Metadata-Version: 2.4
Name: pytubesearch
Version: 1.0.0
Summary: A Python package for searching YouTube by keywords
Author-email: Malith Rukshan <hello@malith.dev>
Maintainer-email: Malith Rukshan <hello@malith.dev>
License-Expression: MIT
Project-URL: Homepage, https://github.com/Malith-Rukshan/PyTubeSearch
Project-URL: Repository, https://github.com/Malith-Rukshan/PyTubeSearch
Project-URL: Issues, https://github.com/Malith-Rukshan/PyTubeSearch/issues
Project-URL: Documentation, https://github.com/Malith-Rukshan/PyTubeSearch/blob/main/README.md
Keywords: youtube,search,api,video,youtube-search
Classifier: Development Status :: 4 - Beta
Classifier: Intended Audience :: Developers
Classifier: Operating System :: OS Independent
Classifier: Programming Language :: Python :: 3
Classifier: Programming Language :: Python :: 3.8
Classifier: Programming Language :: Python :: 3.9
Classifier: Programming Language :: Python :: 3.10
Classifier: Programming Language :: Python :: 3.11
Classifier: Programming Language :: Python :: 3.12
Classifier: Topic :: Internet :: WWW/HTTP :: Dynamic Content
Classifier: Topic :: Multimedia :: Video
Classifier: Topic :: Software Development :: Libraries :: Python Modules
Requires-Python: >=3.8
License-File: LICENSE
Requires-Dist: httpx>=0.24.0
Requires-Dist: pydantic>=2.0.0
Provides-Extra: dev
Requires-Dist: black>=23.0.0; extra == "dev"
Requires-Dist: isort>=5.12.0; extra == "dev"
Requires-Dist: flake8>=6.0.0; extra == "dev"
Requires-Dist: flake8-docstrings>=1.7.0; extra == "dev"
Requires-Dist: flake8-import-order>=0.18.2; extra == "dev"
Requires-Dist: pre-commit>=3.0.0; extra == "dev"
Requires-Dist: mypy>=1.0.0; extra == "dev"
Requires-Dist: types-requests>=2.28.0; extra == "dev"
Requires-Dist: sphinx>=6.0.0; extra == "dev"
Requires-Dist: sphinx-rtd-theme>=1.2.0; extra == "dev"
Requires-Dist: build>=0.10.0; extra == "dev"
Requires-Dist: twine>=4.0.0; extra == "dev"
Provides-Extra: test
Requires-Dist: pytest>=7.0.0; extra == "test"
Requires-Dist: pytest-asyncio>=0.21.0; extra == "test"
Requires-Dist: pytest-cov>=4.0.0; extra == "test"
Requires-Dist: pytest-mock>=3.10.0; extra == "test"
Requires-Dist: pytest-xdist>=3.0.0; extra == "test"
Requires-Dist: coverage>=7.0.0; extra == "test"
Requires-Dist: codecov>=2.1.0; extra == "test"
Requires-Dist: bandit>=1.7.0; extra == "test"
Requires-Dist: safety>=2.3.0; extra == "test"
Requires-Dist: pytest-benchmark>=4.0.0; extra == "test"
Dynamic: license-file
